feedback/__init__.py
feedback/admin.py
feedback/apps.py
feedback/forms.py
feedback/models.py
feedback/test_urls.py
feedback/urls.py
feedback/views.py
feedback/migrations/0001_initial.py
feedback/migrations/0002_auto_20161015_0706.py
feedback/migrations/0003_auto_20161109_0713.py
feedback/migrations/__init__.py
feedback/static/feedback/images/guide_handshapes.gif
feedback/static/feedback/images/guide_movecontact.gif
feedback/static/feedback/images/guide_movedirection.gif
feedback/static/feedback/images/guide_movehands.gif
feedback/static/feedback/images/guide_moveinteraction.gif
feedback/static/feedback/images/guide_movetype.gif
feedback/static/feedback/images/guide_relativesignpos.gif
feedback/static/feedback/images/guide_signpos.gif
feedback/static/feedback/js/jquery-1.11.0.min.js
feedback/templates/feedback/generalfeedback_form.html
feedback/templates/feedback/index.html
feedback/templates/feedback/missingsign_form.html
feedback/templates/feedback/show.html
feedback/templates/feedback/signfeedback_form.html
signbank_feedback-0.3.0.dist-info/DESCRIPTION.rst
signbank_feedback-0.3.0.dist-info/METADATA
signbank_feedback-0.3.0.dist-info/RECORD
signbank_feedback-0.3.0.dist-info/WHEEL
signbank_feedback-0.3.0.dist-info/metadata.json
signbank_feedback-0.3.0.dist-info/top_level.txt
