Metadata-Version: 2.0
Name: signbank-feedback
Version: 0.3.0
Summary: The feedback component of Signbank
Home-page: https://github.com/hujosh/signbank-feedback
Author: Joshua Goddard
Author-email: joshua.goddard@students.mq.edu.au
License: BSD
Keywords: signbank-feedback
Platform: UNKNOWN
Classifier: Development Status :: 3 - Alpha
Classifier: Framework :: Django
Classifier: Framework :: Django :: 1.10
Classifier: Intended Audience :: Developers
Classifier: License :: OSI Approved :: BSD License
Classifier: Natural Language :: English
Classifier: Programming Language :: Python :: 2
Classifier: Programming Language :: Python :: 2.7
Classifier: Programming Language :: Python :: 3
Classifier: Programming Language :: Python :: 3.4
Classifier: Programming Language :: Python :: 3.5
Requires-Dist: django-model-utils (>=2.0)
